{"responses":{"200":{"description":"OK","content":{"application/json":{"schema":{"type":"array","items":{"type":"object","properties":{"value":{"type":"string","description":"Business industry group","nullable":true,"example":"retail"},"name":{"type":"string","description":"Business industry group name","nullable":true,"example":"Retail"},"industries":{"type":"array","items":{"type":"object","properties":{"value":{"type":"string","description":"Business industry","nullable":true,"example":"attorneys_lawyers"},"name":{"type":"string","description":"Business industry name","nullable":true,"example":"Attorneys and lawyers"},"supported":{"type":"boolean","description":"Flag if the business industry is supported","example":true}},"additionalProperties":false,"title":"BusinessIndustry"},"description":"List of business industries for the group","nullable":true}},"additionalProperties":false,"title":"BusinessIndustryGroup"}}}}},"400":{"description":"Bad Request","content":{"application/json":{"schema":{"type":"object","properties":{"errors":{"type":"object","additionalProperties":{"type":"array","items":{"type":"string"}},"nullable":true},"type":{"type":"string","nullable":true},"title":{"type":"string","nullable":true},"status":{"type":"integer","format":"int32","nullable":true},"detail":{"type":"string","nullable":true},"instance":{"type":"string","nullable":true}},"additionalProperties":{},"title":"ValidationProblemDetails"}}}},"401":{"description":"Unauthorized","content":{"application/json":{"schema":{"type":"object","properties":{"type":{"type":"string","nullable":true},"title":{"type":"string","nullable":true},"status":{"type":"integer","format":"int32","nullable":true},"detail":{"type":"string","nullable":true},"instance":{"type":"string","nullable":true}},"additionalProperties":{},"title":"ProblemDetails"}}}},"403":{"description":"Forbidden","content":{"application/json":{"schema":{"type":"object","properties":{"type":{"type":"string","nullable":true},"title":{"type":"string","nullable":true},"status":{"type":"integer","format":"int32","nullable":true},"detail":{"type":"string","nullable":true},"instance":{"type":"string","nullable":true}},"additionalProperties":{},"title":"ProblemDetails"}}}},"404":{"description":"Not Found","content":{"application/json":{"schema":{"type":"object","properties":{"type":{"type":"string","nullable":true},"title":{"type":"string","nullable":true},"status":{"type":"integer","format":"int32","nullable":true},"detail":{"type":"string","nullable":true},"instance":{"type":"string","nullable":true}},"additionalProperties":{},"title":"ProblemDetails"}}}}}}